nonebot_plugin_more_rules/__init__.py
nonebot_plugin_more_rules/chain_rule.py
nonebot_plugin_more_rules/pinyin_rule.py
nonebot_plugin_more_rules/throttle_rule.py
nonebot_plugin_more_rules-0.0.0.dist-info/LICENSE
nonebot_plugin_more_rules-0.0.0.dist-info/METADATA
nonebot_plugin_more_rules-0.0.0.dist-info/WHEEL
nonebot_plugin_more_rules-0.0.0.dist-info/top_level.txt
nonebot_plugin_more_rules-0.0.0.dist-info/RECORD
