Metadata-Version: 2.2
Name: nonebot_plugin_more_rules
Version: 0.0.0
Summary: 更多符合 NoneBot2 规范的响应规则
Author-email: Drelf2018 <drelf2018@gmail.com>
License: MIT License
Keywords: NoneBot2,Rule
Requires-Python: >=3.8
License-File: LICENSE
Requires-Dist: nonebot2
Requires-Dist: pypinyin
